autogram/__init__.py
autogram/actions.py
autogram/autogram.py
autogram/base.py
autogram/config.py
autogram/types.py
autogram-4.0.0.dist-info/LICENSE
autogram-4.0.0.dist-info/METADATA
autogram-4.0.0.dist-info/WHEEL
autogram-4.0.0.dist-info/top_level.txt
autogram-4.0.0.dist-info/RECORD
