Metadata-Version: 2.2
Name: autogram
Version: 4.0.0
Summary: An easily extensible telegram API wrapper
Author-email: drui9 <drui9@duck.com>
License: MIT License
Project-URL: Homepage, https://github.com/drui9/autogram
Keywords: autogram,telegram,API,wrapper
Classifier: License :: OSI Approved :: MIT License
Classifier: Programming Language :: Python
Classifier: Programming Language :: Python :: 3
Requires-Python: >=3.12
License-File: LICENSE
Requires-Dist: loguru
Requires-Dist: requests
Provides-Extra: dev
Requires-Dist: build; extra == "dev"
Requires-Dist: twine; extra == "dev"
Requires-Dist: watchdog; extra == "dev"
